setup.py
pyfix/__init__.py
pyfix/cli.py
pyfix/decorators.py
pyfix/fixture.py
pyfix/testcollector.py
pyfix/testdefinition.py
pyfix/testrunner.py
pyfix/utils.py
pyfix.egg-info/PKG-INFO
pyfix.egg-info/SOURCES.txt
pyfix.egg-info/dependency_links.txt
pyfix.egg-info/requires.txt
pyfix.egg-info/top_level.txt
pyfix.egg-info/zip-safe